AnimatedGraphs/AnimatedBar.py
AnimatedGraphs/__init__.py
AnimatedGraphs/version.py
AnimatedGraphs-1.0.dist-info/LICENSE.txt
AnimatedGraphs-1.0.dist-info/METADATA
AnimatedGraphs-1.0.dist-info/WHEEL
AnimatedGraphs-1.0.dist-info/top_level.txt
AnimatedGraphs-1.0.dist-info/RECORD
