Metadata-Version: 2.1
Name: AnimatedGraphs
Version: 1.0
Summary: Build and awesome animated graph easily
Home-page: https://github.com/lgbaeza/animatedgraph-pkg
Author: Luis Gerado Baeza
Author-email: lgbaezac@gmail.com
License: MIT
Download-URL: https://github.com/lgbaeza/animatedgraph-pkg/archive/1.0.tar.gz
Keywords: Animated,Graph,Visualisation
Platform: UNKNOWN
Classifier: Development Status :: 4 - Beta
Classifier: Intended Audience :: Developers
Classifier: Topic :: Software Development :: Build Tools
Classifier: License :: OSI Approved :: MIT License
Classifier: Programming Language :: Python :: 3
Classifier: Programming Language :: Python :: 3.4
Classifier: Programming Language :: Python :: 3.5
Classifier: Programming Language :: Python :: 3.6
Requires-Dist: imageio
Requires-Dist: pandas
Requires-Dist: IPython
Requires-Dist: numpy
Requires-Dist: requests
Requires-Dist: matplotlib
